orgparse/__init__.py
orgparse/date.py
orgparse/extra.py
orgparse/inline.py
orgparse/node.py
orgparse/py.typed
orgparse/tests/__init__.py
orgparse/tests/test_data.py
orgparse/tests/test_date.py
orgparse/tests/test_hugedata.py
orgparse/tests/test_misc.py
orgparse/tests/test_rich.py
orgparse/tests/data/00_simple.org
orgparse/tests/data/00_simple.py
orgparse/tests/data/01_attributes.org
orgparse/tests/data/01_attributes.py
orgparse/tests/data/02_tree_struct.org
orgparse/tests/data/02_tree_struct.py
orgparse/tests/data/03_repeated_tasks.org
orgparse/tests/data/03_repeated_tasks.py
orgparse/tests/data/04_logbook.org
orgparse/tests/data/04_logbook.py
orgparse/tests/data/05_tags.org
orgparse/tests/data/05_tags.py
orgparse/tests/data/__init__.py
orgparse-0.4.20250520.dist-info/METADATA
orgparse-0.4.20250520.dist-info/WHEEL
orgparse-0.4.20250520.dist-info/licenses/LICENSE
orgparse-0.4.20250520.dist-info/RECORD
