Metadata-Version: 2.4
Name: orgparse
Version: 0.4.20250520
Summary: orgparse - Emacs org-mode parser in Python
Project-URL: Homepage, https://github.com/karlicoss/orgparse
Author-email: "Takafumi Arakaki (@tkf)" <aka.tkf@gmail.com>, "Dmitrii Gerasimov (@karlicoss)" <karlicoss@gmail.com>
Maintainer-email: "Dmitrii Gerasimov (@karlicoss)" <karlicoss@gmail.com>
License: BSD 2-Clause License
License-File: LICENSE
Keywords: emacs,org,org-mode
Classifier: Development Status :: 5 - Production/Stable
Classifier: License :: OSI Approved :: BSD License
Classifier: Topic :: Text Processing :: Markup
Requires-Python: >=3.9
